iac_memory_mcp_server/__init__.py
iac_memory_mcp_server/__main__.py
iac_memory_mcp_server/context.py
iac_memory_mcp_server/prompts.py
iac_memory_mcp_server/resources.py
iac_memory_mcp_server/schema.sql
iac_memory_mcp_server/server.py
iac_memory_mcp_server/shared.py
iac_memory_mcp_server/db/__init__.py
iac_memory_mcp_server/db/ansible.py
iac_memory_mcp_server/db/connection.py
iac_memory_mcp_server/db/core.py
iac_memory_mcp_server/db/entities.py
iac_memory_mcp_server/db/resources.py
iac_memory_mcp_server/db/terraform.py
iac_memory_mcp_server/db/tools.py
iac_memory_mcp_server/tools/__init__.py
iac_memory_mcp_server/tools/ansible.py
iac_memory_mcp_server/tools/base.py
iac_memory_mcp_server/tools/entity.py
iac_memory_mcp_server/tools/terraform.py
iac_memory_mcp_server/utils/errors.py
mseep_iac_memory_mcp_server-0.1.3.dist-info/licenses/LICENSE
tests/__init__.py
tests/conftest.py
tests/test_async_sync.py
tests/test_context.py
tests/test_database_methods.py
tests/test_integration.py
tests/test_mcp_compliance.py
tests/test_mcp_logging.py
tests/test_performance.py
tests/test_resource_templates.py
tests/test_unit.py
tests/test_utils/__init__.py
tests/test_utils/base_utils.py
tests/test_utils/db_utils.py
tests/test_utils/exceptions.py
tests/test_utils/mcp_utils.py
mseep_iac_memory_mcp_server-0.1.3.dist-info/METADATA
mseep_iac_memory_mcp_server-0.1.3.dist-info/WHEEL
mseep_iac_memory_mcp_server-0.1.3.dist-info/entry_points.txt
mseep_iac_memory_mcp_server-0.1.3.dist-info/top_level.txt
mseep_iac_memory_mcp_server-0.1.3.dist-info/RECORD
